string_data_algorithms/__init__.py
string_data_algorithms/string_data_manipulators.py
string_data_algorithms/test_string_data_manipulators.py
string_data_algorithms-0.1.3.dist-info/METADATA
string_data_algorithms-0.1.3.dist-info/WHEEL
string_data_algorithms-0.1.3.dist-info/top_level.txt
string_data_algorithms-0.1.3.dist-info/RECORD
