Metadata-Version: 2.1
Name: string-data-algorithms
Version: 0.1.3
Summary: Working with string data
Home-page: https://github.com/davitkv8/Hire-Learn
Author: Davit Kvaratskhelia
Author-email: davit.kv8@gmail.com
